src/butterfly.v
`timescale 1ns/1ps
// butterfly.v
// Radix-2 DIT butterfly unit for use in fft1d_64.
// Computes:
//   out_re_a = in_re_a + (W_re*in_re_b - W_im*in_im_b)
//   out_im_a = in_im_a + (W_re*in_im_b + W_im*in_re_b)
//   out_re_b = in_re_a - (W_re*in_re_b - W_im*in_im_b)
//   out_im_b = in_im_a - (W_re*in_im_b + W_im*in_re_b)

module butterfly #(
    parameter DATA_WIDTH = 16,  // total bits (Q8.8)
    parameter FRAC       = 8,   // fractional bits
    parameter SCALE_EN   = 1    // 1 = >>>1 per stage (scaled FFT), 0 = no scaling
)(
    input  wire signed [DATA_WIDTH-1:0] in_re_a,
    input  wire signed [DATA_WIDTH-1:0] in_im_a,
    input  wire signed [DATA_WIDTH-1:0] in_re_b,
    input  wire signed [DATA_WIDTH-1:0] in_im_b,
    input  wire signed [DATA_WIDTH-1:0] w_re,   // twiddle real
    input  wire signed [DATA_WIDTH-1:0] w_im,   // twiddle imag

    output wire signed [DATA_WIDTH-1:0] out_re_a,
    output wire signed [DATA_WIDTH-1:0] out_im_a,
    output wire signed [DATA_WIDTH-1:0] out_re_b,
    output wire signed [DATA_WIDTH-1:0] out_im_b
);

    // Q8.8 × Q8.8 → Q16.16 in 32 bits. Keep bits [23:8] to recover Q8.8.
    localparam MSB = FRAC + DATA_WIDTH - 1;   // 23
    localparam LSB = FRAC;                     // 8

    // Twiddle product:  tw = W * b  (complex multiply)
    wire signed [2*DATA_WIDTH-1:0] tw_re_full = (w_re * in_re_b) - (w_im * in_im_b);
    wire signed [2*DATA_WIDTH-1:0] tw_im_full = (w_re * in_im_b) + (w_im * in_re_b);

    wire signed [DATA_WIDTH-1:0] tw_re = tw_re_full[MSB:LSB];
    wire signed [DATA_WIDTH-1:0] tw_im = tw_im_full[MSB:LSB];

    // Butterfly: sum and difference.
    // If SCALE_EN=1, apply >>>1 (scaled FFT) to prevent overflow.
    // If SCALE_EN=0, no scaling (used for IFFT to preserve magnitude).
    generate
        if (SCALE_EN) begin : scaled
            assign out_re_a = (in_re_a + tw_re) >>> 1;
            assign out_im_a = (in_im_a + tw_im) >>> 1;
            assign out_re_b = (in_re_a - tw_re) >>> 1;
            assign out_im_b = (in_im_a - tw_im) >>> 1;
        end else begin : unscaled
            assign out_re_a = in_re_a + tw_re;
            assign out_im_a = in_im_a + tw_im;
            assign out_re_b = in_re_a - tw_re;
            assign out_im_b = in_im_a - tw_im;
        end
    endgenerate

endmodule

src/twiddle_rom_32.v
`timescale 1ns/1ps
// twiddle_rom_32.v
// ROM of twiddle factors W_32^k = exp(-j2πk/32) for k = 0..15.
// Stored interleaved in twiddle_32.mem: line 2k = real, line 2k+1 = imag.
// Q8.8 signed fixed-point.

module twiddle_rom_32 #(
    parameter N          = 32,
    parameter DATA_WIDTH = 16,
    parameter FRAC       = 8
)(
    input  wire [$clog2(N/2)-1:0]       addr,   // k = 0..15
    output wire signed [DATA_WIDTH-1:0] w_re,
    output wire signed [DATA_WIDTH-1:0] w_im
);

    // Flat array: 32 entries (16 pairs × 2)
    reg signed [DATA_WIDTH-1:0] mem [0:N-1];

    initial begin
        $readmemh("data/twiddle_32.mem", mem);
    end

    // addr*2 = {addr, 1'b0},  addr*2+1 = {addr, 1'b1}
    assign w_re = mem[{addr, 1'b0}];
    assign w_im = mem[{addr, 1'b1}];

endmodule

src/fft1d_32.v
`timescale 1ns/1ps
// fft1d_32.v
// 32-point radix-2 DIT FFT, iterative single-butterfly architecture.
// log2(32) = 5 stages, 16 butterfly ops per stage = 80 cycles per transform.
// Uses scaled butterfly (>>>1 per stage) to prevent overflow.

module fft1d_32 #(
    parameter N          = 32,
    parameter DATA_WIDTH = 16,
    parameter FRAC       = 8,
    parameter SCALE_EN   = 1    // 1 = >>>1 per stage (forward FFT), 0 = no scaling (IFFT)
)(
    input  wire                          clk,
    input  wire                          rst_n,
    input  wire                          start,
    input  wire signed [DATA_WIDTH-1:0]  in_re [0:N-1],
    input  wire signed [DATA_WIDTH-1:0]  in_im [0:N-1],
    output reg  signed [DATA_WIDTH-1:0]  out_re [0:N-1],
    output reg  signed [DATA_WIDTH-1:0]  out_im [0:N-1],
    output reg                           done
);

    // ── FSM states ──────────────────────────────────────────────────────
    localparam S_IDLE    = 3'd0;
    localparam S_BITREV  = 3'd1;
    localparam S_STAGE   = 3'd2;
    localparam S_OUTPUT  = 3'd3;
    localparam S_DONE    = 3'd4;

    reg [2:0] state;

    // ── Working buffer ──────────────────────────────────────────────────
    reg signed [DATA_WIDTH-1:0] buf_re [0:N-1];
    reg signed [DATA_WIDTH-1:0] buf_im [0:N-1];

    // ── Stage counters ──────────────────────────────────────────────────
    reg [2:0]  stage_cnt;     // current FFT stage (0..4)
    reg [3:0]  bfly_cnt;      // butterfly index within stage (0..15)

    // ── Bit-reversal lookup (hardcoded for N=32, 5-bit reversal) ────────
    // bit_rev[i] = reverse of i's 5-bit binary representation
    function [4:0] bit_rev;
        input [4:0] idx;
        begin
            bit_rev = {idx[0], idx[1], idx[2], idx[3], idx[4]};
        end
    endfunction

    // ── Butterfly address computation ───────────────────────────────────
    // At stage s, butterflies operate on pairs separated by half = 2^s.
    // Group size = 2^(s+1). Number of groups = N / group.
    // For butterfly b (0..15):
    //   group_idx = b >> s         (which group)
    //   bfly_in_group = b & ((1<<s)-1)  (position within group)
    //   idx_a = group_idx * (2 << s) + bfly_in_group
    //   idx_b = idx_a + (1 << s)
    //   tw_addr = bfly_in_group * (N/2 >> s)

    wire [4:0] half  = 5'd1 << stage_cnt;         // 1, 2, 4, 8, 16
    wire [4:0] group = 5'd1 << (stage_cnt + 1);   // 2, 4, 8, 16, 32

    // Decompose bfly_cnt into group index and position within group
    wire [3:0] grp_idx;
    wire [3:0] bfly_in_grp;

    // grp_idx  = bfly_cnt >> stage_cnt
    // bfly_pos = bfly_cnt & (half - 1)
    assign grp_idx    = bfly_cnt >> stage_cnt;
    assign bfly_in_grp = bfly_cnt & (half[3:0] - 4'd1);

    wire [4:0] idx_a = grp_idx * group + bfly_in_grp;
    wire [4:0] idx_b = idx_a + half;

    // Twiddle address: k = bfly_in_grp * (N/2 / half) = bfly_in_grp << (4 - stage_cnt)
    wire [3:0] tw_addr = bfly_in_grp << (3'd4 - stage_cnt);

    // ── Twiddle ROM ─────────────────────────────────────────────────────
    wire signed [DATA_WIDTH-1:0] w_re, w_im;

    twiddle_rom_32 #(.N(N), .DATA_WIDTH(DATA_WIDTH), .FRAC(FRAC)) u_trom (
        .addr(tw_addr),
        .w_re(w_re),
        .w_im(w_im)
    );

    // ── Butterfly unit (combinational) ──────────────────────────────────
    wire signed [DATA_WIDTH-1:0] bf_out_re_a, bf_out_im_a;
    wire signed [DATA_WIDTH-1:0] bf_out_re_b, bf_out_im_b;

    butterfly #(.DATA_WIDTH(DATA_WIDTH), .FRAC(FRAC), .SCALE_EN(SCALE_EN)) u_bfly (
        .in_re_a(buf_re[idx_a]), .in_im_a(buf_im[idx_a]),
        .in_re_b(buf_re[idx_b]), .in_im_b(buf_im[idx_b]),
        .w_re(w_re),             .w_im(w_im),
        .out_re_a(bf_out_re_a),  .out_im_a(bf_out_im_a),
        .out_re_b(bf_out_re_b),  .out_im_b(bf_out_im_b)
    );

    // ── Main FSM ────────────────────────────────────────────────────────
    integer i;

    always @(posedge clk or negedge rst_n) begin
        if (!rst_n) begin
            state     <= S_IDLE;
            stage_cnt <= 0;
            bfly_cnt  <= 0;
            done      <= 0;
        end else begin
            done <= 0;   // default: de-assert

            case (state)

                S_IDLE: begin
                    if (start) begin
                        state <= S_BITREV;
                    end
                end

                // Load inputs into buffer in bit-reversed order (1 cycle)
                S_BITREV: begin
                    for (i = 0; i < N; i = i + 1) begin
                        buf_re[bit_rev(i[4:0])] <= in_re[i];
                        buf_im[bit_rev(i[4:0])] <= in_im[i];
                    end
                    stage_cnt <= 0;
                    bfly_cnt  <= 0;
                    state     <= S_STAGE;
                end

                // Execute one butterfly per clock cycle
                S_STAGE: begin
                    buf_re[idx_a] <= bf_out_re_a;
                    buf_im[idx_a] <= bf_out_im_a;
                    buf_re[idx_b] <= bf_out_re_b;
                    buf_im[idx_b] <= bf_out_im_b;

                    if (bfly_cnt == 4'd15) begin
                        // Finished all 16 butterflies in this stage
                        bfly_cnt <= 0;
                        if (stage_cnt == 3'd4) begin
                            // All 5 stages done
                            state <= S_OUTPUT;
                        end else begin
                            stage_cnt <= stage_cnt + 1;
                        end
                    end else begin
                        bfly_cnt <= bfly_cnt + 1;
                    end
                end

                // Copy buffer to outputs (1 cycle)
                S_OUTPUT: begin
                    for (i = 0; i < N; i = i + 1) begin
                        out_re[i] <= buf_re[i];
                        out_im[i] <= buf_im[i];
                    end
                    state <= S_DONE;
                end

                S_DONE: begin
                    done  <= 1;
                    state <= S_IDLE;
                end

            endcase
        end
    end

endmodule

tb/tb_fft1d_32.v
`timescale 1ns/1ps
// tb_fft1d_32.v
// Unit testbench for fft1d_32.v (32-point 1D FFT)
// Test 1: DC impulse — in[0]=1/32, rest=0 → all outputs ≈ 1/32 (scaled FFT)
// Test 2: All-ones  — every in[n]=1/32 → out[0] = 1/32, rest ≈ 0

module tb_fft1d_32;

    parameter N          = 32;
    parameter DATA_WIDTH = 16;
    parameter FRAC       = 8;

    reg  clk = 0, rst_n = 0, start = 0;
    reg  signed [DATA_WIDTH-1:0] in_re [0:N-1];
    reg  signed [DATA_WIDTH-1:0] in_im [0:N-1];
    wire signed [DATA_WIDTH-1:0] out_re [0:N-1];
    wire signed [DATA_WIDTH-1:0] out_im [0:N-1];
    wire done;

    always #5 clk = ~clk;

    fft1d_32 #(.N(N), .DATA_WIDTH(DATA_WIDTH), .FRAC(FRAC)) dut (
        .clk(clk), .rst_n(rst_n), .start(start),
        .in_re(in_re), .in_im(in_im),
        .out_re(out_re), .out_im(out_im),
        .done(done)
    );

    integer i;
    integer errors;

    initial begin
        $dumpfile("fft1d_32.vcd");
        $dumpvars(0, tb_fft1d_32);

        // ── Test 1: DC impulse ──────────────────────────────────────
        // Input: x[0] = 0.125 (0x0020 in Q8.8), x[1..31] = 0
        // After 5 butterfly stages with >>>1 scaling, the DC input
        // gets divided by 2^5 = 32 total. So input of 0.125 should
        // give output ≈ 0.125/32 ≈ 0.004 for all bins.
        // Let's use a larger value: x[0] = 1.0 (0x0100)
        // Expected: each output ≈ 1.0 / 32 = 0.03125 (0x0008)
        $display("\n══ Test 1: DC impulse ══");
        for (i = 0; i < N; i = i + 1) begin
            in_re[i] = (i == 0) ? 16'sh0100 : 16'sh0000;
            in_im[i] = 16'sh0000;
        end

        rst_n = 0; #20; rst_n = 1; #10;
        @(posedge clk); start <= 1;
        @(posedge clk); start <= 0;

        @(posedge done);
        @(posedge clk);

        errors = 0;
        for (i = 0; i < N; i = i + 1) begin
            // With scaled FFT (>>>1 each stage), DC impulse should give
            // roughly 1/32 = 0x0008 for real, 0 for imag at each bin
            if (out_im[i] != 0) begin
                $display("  Bin %2d: re=%6d im=%6d  [imag non-zero!]", i, out_re[i], out_im[i]);
                errors = errors + 1;
            end
        end
        $display("  Bin[0] = re=%0d (expect ~8), im=%0d (expect 0)", out_re[0], out_im[0]);
        $display("  Bin[1] = re=%0d (expect ~8), im=%0d (expect 0)", out_re[1], out_im[1]);
        if (errors == 0)
            $display("  PASS: All imaginary parts are zero.");
        else
            $display("  %0d bins had non-zero imag (may be truncation noise).", errors);

        // ── Test 2: All ones ────────────────────────────────────────
        // Input: all x[n] = 0.25 (0x0040)
        // FFT of constant = N*const at bin 0, zero elsewhere.
        // With scaled FFT: bin[0] = 0.25 (no growth since add+shift cancels)
        // Other bins: should be zero
        $display("\n══ Test 2: All ones ══");
        for (i = 0; i < N; i = i + 1) begin
            in_re[i] = 16'sh0040;  // 0.25 in Q8.8
            in_im[i] = 16'sh0000;
        end

        @(posedge clk); start <= 1;
        @(posedge clk); start <= 0;

        @(posedge done);
        @(posedge clk);

        $display("  Bin[0] = re=%0d im=%0d", out_re[0], out_im[0]);
        $display("  Bin[1] = re=%0d im=%0d (expect ~0)", out_re[1], out_im[1]);
        $display("  Bin[16] = re=%0d im=%0d (expect ~0)", out_re[16], out_im[16]);

        #100;
        $display("\nAll tests complete.");
        $finish;
    end

endmodule

fft1d_32.vcd
$date
	Sun Mar 08 12:59:38 2026
$end
$version
	Icarus Verilog
$end
$timescale
	1ps
$end
$scope module tb_fft1d_32 $end
$var wire 1 ! done $end
$var parameter 32 " DATA_WIDTH $end
$var parameter 32 # FRAC $end
$var parameter 32 $ N $end
$var reg 1 % clk $end
$var reg 1 & rst_n $end
$var reg 1 ' start $end
$var integer 32 ( errors [31:0] $end
$var integer 32 ) i [31:0] $end
$scope module dut $end
$var wire 4 * bfly_in_grp [3:0] $end
$var wire 1 % clk $end
$var wire 1 & rst_n $end
$var wire 1 ' start $end
$var wire 16 + w_re [15:0] $end
$var wire 16 , w_im [15:0] $end
$var wire 4 - tw_addr [3:0] $end
$var wire 5 . idx_b [4:0] $end
$var wire 5 / idx_a [4:0] $end
$var wire 5 0 half [4:0] $end
$var wire 4 1 grp_idx [3:0] $end
$var wire 5 2 group [4:0] $end
$var wire 16 3 bf_out_re_b [15:0] $end
$var wire 16 4 bf_out_re_a [15:0] $end
$var wire 16 5 bf_out_im_b [15:0] $end
$var wire 16 6 bf_out_im_a [15:0] $end
$var parameter 32 7 DATA_WIDTH $end
$var parameter 32 8 FRAC $end
$var parameter 32 9 N $end
$var parameter 3 : S_BITREV $end
$var parameter 3 ; S_DONE $end
$var parameter 3 < S_IDLE $end
$var parameter 3 = S_OUTPUT $end
$var parameter 3 > S_STAGE $end
$var reg 4 ? bfly_cnt [3:0] $end
$var reg 1 ! done $end
$var reg 3 @ stage_cnt [2:0] $end
$var reg 3 A state [2:0] $end
$var integer 32 B i [31:0] $end
$scope function bit_rev $end
$var reg 5 C idx [4:0] $end
$upscope $end
$scope module u_bfly $end
$var wire 16 D in_im_a [15:0] $end
$var wire 16 E in_im_b [15:0] $end
$var wire 16 F in_re_a [15:0] $end
$var wire 16 G in_re_b [15:0] $end
$var wire 16 H w_re [15:0] $end
$var wire 16 I w_im [15:0] $end
$var wire 32 J tw_re_full [31:0] $end
$var wire 16 K tw_re [15:0] $end
$var wire 32 L tw_im_full [31:0] $end
$var wire 16 M tw_im [15:0] $end
$var wire 16 N out_re_b [15:0] $end
$var wire 16 O out_re_a [15:0] $end
$var wire 16 P out_im_b [15:0] $end
$var wire 16 Q out_im_a [15:0] $end
$var parameter 32 R DATA_WIDTH $end
$var parameter 32 S FRAC $end
$var parameter 32 T LSB $end
$var parameter 34 U MSB $end
$upscope $end
$scope module u_trom $end
$var wire 4 V addr [3:0] $end
$var wire 16 W w_im [15:0] $end
$var wire 16 X w_re [15:0] $end
$var parameter 32 Y DATA_WIDTH $end
$var parameter 32 Z FRAC $end
$var parameter 32 [ N $end
$upscope $end
$upscope $end
$upscope $end
$enddefinitions $end
$comment Show the parameter values. $end
$dumpall
b100000 [
b1000 Z
b10000 Y
b10111 U
b1000 T
b1000 S
b10000 R
b10 >
b11 =
b0 <
b100 ;
b1 :
b100000 9
b1000 8
b10000 7
b100000 $
b1000 #
b10000 "
$end
#0
$dumpvars
bx X
bx W
bx V
bx Q
bx P
bx O
bx N
bx M
bx L
bx K
bx J
bx I
bx H
bx G
bx F
bx E
bx D
bx C
bx B
bx A
bx @
bx ?
bx 6
bx 5
bx 4
bx 3
bx 2
bx 1
bx 0
bx /
bx .
bx -
bx ,
bx +
bx *
b100000 )
bx (
0'
0&
0%
x!
$end
#5000
b1 .
b0 /
b0 *
0!
b0 1
b0 ?
b1 0
b10 2
b100000000 +
b100000000 H
b100000000 X
b0 ,
b0 I
b0 W
b0 -
b0 V
b0 @
b0 A
1%
#10000
0%
#15000
1%
#20000
0%
1&
#25000
1%
#30000
0%
#35000
1'
1%
#40000
0%
#45000
b1 A
0'
1%
#50000
0%
#55000
b10000000 4
b10000000 O
b10000000 3
b10000000 N
b0 6
b0 Q
b0 5
b0 P
b0 K
b0 M
b10 A
b0 J
b0 L
b0 E
b0 G
b0 D
b100000000 F
b11111 C
b100000 B
1%
#60000
0%
#65000
b0 4
b0 O
b0 3
b0 N
b11 .
b10 /
b1 1
b1 ?
b0 J
b0 G
b0 F
1%
#70000
0%
#75000
b101 .
b100 /
b10 1
b10 ?
1%
#80000
0%
#85000
b111 .
b110 /
b11 1
b11 ?
1%
#90000
0%
#95000
b1001 .
b1000 /
b100 1
b100 ?
1%
#100000
0%
#105000
b1011 .
b1010 /
b101 1
b101 ?
1%
#110000
0%
#115000
b1101 .
b1100 /
b110 1
b110 ?
1%
#120000
0%
#125000
b1111 .
b1110 /
b111 1
b111 ?
1%
#130000
0%
#135000
b10001 .
b10000 /
b1000 1
b1000 ?
1%
#140000
0%
#145000
b10011 .
b10010 /
b1001 1
b1001 ?
1%
#150000
0%
#155000
b10101 .
b10100 /
b1010 1
b1010 ?
1%
#160000
0%
#165000
b10111 .
b10110 /
b1011 1
b1011 ?
1%
#170000
0%
#175000
b11001 .
b11000 /
b1100 1
b1100 ?
1%
#180000
0%
#185000
b11011 .
b11010 /
b1101 1
b1101 ?
1%
#190000
0%
#195000
b11101 .
b11100 /
b1110 1
b1110 ?
1%
#200000
0%
#205000
b11111 .
b11110 /
b1111 1
b1111 ?
1%
#210000
0%
#215000
b1000000 4
b1000000 O
b1000000 3
b1000000 N
b10 0
b100 2
b1 @
b0 J
b0 G
b10 .
b10000000 F
b0 /
b0 1
b0 ?
1%
#220000
0%
#225000
b11 .
b1 /
b0 +
b0 H
b0 X
b0 L
b1111111100000000 ,
b1111111100000000 I
b1111111100000000 W
b1000 -
b1000 V
b1 *
b0 K
b1000000 4
b1000000 O
b1000000 3
b1000000 N
b1 ?
b0 J
b0 G
b10000000 F
1%
#230000
0%
#235000
b100000000 +
b100000000 H
b100000000 X
b0 ,
b0 I
b0 W
b0 -
b0 V
b0 *
b0 4
b0 O
b0 3
b0 N
b110 .
b100 /
b1 1
b10 ?
b0 L
b0 G
b0 F
1%
#240000
0%
#245000
b111 .
b101 /
b0 +
b0 H
b0 X
b1111111100000000 ,
b1111111100000000 I
b1111111100000000 W
b1000 -
b1000 V
b1 *
b11 ?
1%
#250000
0%
#255000
b100000000 +
b100000000 H
b100000000 X
b0 ,
b0 I
b0 W
b0 -
b0 V
b0 *
b1010 .
b1000 /
b10 1
b100 ?
1%
#260000
0%
#265000
b1011 .
b1001 /
b0 +
b0 H
b0 X
b1111111100000000 ,
b1111111100000000 I
b1111111100000000 W
b1000 -
b1000 V
b1 *
b101 ?
1%
#270000
0%
#275000
b100000000 +
b100000000 H
b100000000 X
b0 ,
b0 I
b0 W
b0 -
b0 V
b0 *
b1110 .
b1100 /
b11 1
b110 ?
1%
#280000
0%
#285000
b1111 .
b1101 /
b0 +
b0 H
b0 X
b1111111100000000 ,
b1111111100000000 I
b1111111100000000 W
b1000 -
b1000 V
b1 *
b111 ?
1%
#290000
0%
#295000
b100000000 +
b100000000 H
b100000000 X
b0 ,
b0 I
b0 W
b0 -
b0 V
b0 *
b10010 .
b10000 /
b100 1
b1000 ?
1%
#300000
0%
#305000
b10011 .
b10001 /
b0 +
b0 H
b0 X
b1111111100000000 ,
b1111111100000000 I
b1111111100000000 W
b1000 -
b1000 V
b1 *
b1001 ?
1%
#310000
0%
#315000
b100000000 +
b100000000 H
b100000000 X
b0 ,
b0 I
b0 W
b0 -
b0 V
b0 *
b10110 .
b10100 /
b101 1
b1010 ?
1%
#320000
0%
#325000
b10111 .
b10101 /
b0 +
b0 H
b0 X
b1111111100000000 ,
b1111111100000000 I
b1111111100000000 W
b1000 -
b1000 V
b1 *
b1011 ?
1%
#330000
0%
#335000
b100000000 +
b100000000 H
b100000000 X
b0 ,
b0 I
b0 W
b0 -
b0 V
b0 *
b11010 .
b11000 /
b110 1
b1100 ?
1%
#340000
0%
#345000
b11011 .
b11001 /
b0 +
b0 H
b0 X
b1111111100000000 ,
b1111111100000000 I
b1111111100000000 W
b1000 -
b1000 V
b1 *
b1101 ?
1%
#350000
0%
#355000
b100000000 +
b100000000 H
b100000000 X
b0 ,
b0 I
b0 W
b0 -
b0 V
b0 *
b11110 .
b11100 /
b111 1
b1110 ?
1%
#360000
0%
#365000
b11111 .
b11101 /
b0 +
b0 H
b0 X
b1111111100000000 ,
b1111111100000000 I
b1111111100000000 W
b1000 -
b1000 V
b1 *
b1111 ?
1%
#370000
0%
#375000
b100000 4
b100000 O
b100000 3
b100000 N
b0 *
b100 0
b1000 2
b0 J
b100000000 +
b100000000 H
b100000000 X
b0 ,
b0 I
b0 W
b0 -
b0 V
b10 @
b0 L
b0 G
b100 .
b1000000 F
b0 /
b0 1
b0 ?
1%
#380000
0%
#385000
b101 .
b1 /
b10110101 +
b10110101 H
b10110101 X
b0 L
b1111111101001011 ,
b1111111101001011 I
b1111111101001011 W
b100 -
b100 V
b1 *
b0 K
b100000 4
b100000 O
b100000 3
b100000 N
b1 ?
b0 J
b0 G
b1000000 F
1%
#390000
0%
#395000
b0 6
b0 Q
b0 5
b0 P
b110 .
b10 /
b0 +
b0 H
b0 X
b1111111100000000 ,
b1111111100000000 I
b1111111100000000 W
b1000 -
b1000 V
b10 *
b0 K
b0 M
b100000 4
b100000 O
b100000 3
b100000 N
b10 ?
b0 J
b0 L
b0 G
b1000000 F
1%
#400000
0%
#405000
b0 6
b0 Q
b0 5
b0 P
b111 .
b11 /
b0 J
b1111111101001011 +
b1111111101001011 H
b1111111101001011 X
b1111111101001011 ,
b1111111101001011 I
b1111111101001011 W
b1100 -
b1100 V
b11 *
b0 M
b100000 4
b100000 O
b100000 3
b100000 N
b11 ?
b0 L
b0 G
b1000000 F
1%
#410000
0%
#415000
b100000000 +
b100000000 H
b100000000 X
b0 ,
b0 I
b0 W
b0 -
b0 V
b0 *
b0 4
b0 O
b0 3
b0 N
b1100 .
b1000 /
b1 1
b100 ?
b0 J
b0 L
b0 G
b0 F
1%
#420000
0%
#425000
b1101 .
b1001 /
b10110101 +
b10110101 H
b10110101 X
b1111111101001011 ,
b1111111101001011 I
b1111111101001011 W
b100 -
b100 V
b1 *
b101 ?
1%
#430000
0%
#435000
b1110 .
b1010 /
b0 +
b0 H
b0 X
b1111111100000000 ,
b1111111100000000 I
b1111111100000000 W
b1000 -
b1000 V
b10 *
b110 ?
1%
#440000
0%
#445000
b1111 .
b1011 /
b1111111101001011 +
b1111111101001011 H
b1111111101001011 X
b1111111101001011 ,
b1111111101001011 I
b1111111101001011 W
b1100 -
b1100 V
b11 *
b111 ?
1%
#450000
0%
#455000
b100000000 +
b100000000 H
b100000000 X
b0 ,
b0 I
b0 W
b0 -
b0 V
b0 *
b10100 .
b10000 /
b10 1
b1000 ?
1%
#460000
0%
#465000
b10101 .
b10001 /
b10110101 +
b10110101 H
b10110101 X
b1111111101001011 ,
b1111111101001011 I
b1111111101001011 W
b100 -
b100 V
b1 *
b1001 ?
1%
#470000
0%
#475000
b10110 .
b10010 /
b0 +
b0 H
b0 X
b1111111100000000 ,
b1111111100000000 I
b1111111100000000 W
b1000 -
b1000 V
b10 *
b1010 ?
1%
#480000
0%
#485000
b10111 .
b10011 /
b1111111101001011 +
b1111111101001011 H
b1111111101001011 X
b1111111101001011 ,
b1111111101001011 I
b1111111101001011 W
b1100 -
b1100 V
b11 *
b1011 ?
1%
#490000
0%
#495000
b100000000 +
b100000000 H
b100000000 X
b0 ,
b0 I
b0 W
b0 -
b0 V
b0 *
b11100 .
b11000 /
b11 1
b1100 ?
1%
#500000
0%
#505000
b11101 .
b11001 /
b10110101 +
b10110101 H
b10110101 X
b1111111101001011 ,
b1111111101001011 I
b1111111101001011 W
b100 -
b100 V
b1 *
b1101 ?
1%
#510000
0%
#515000
b11110 .
b11010 /
b0 +
b0 H
b0 X
b1111111100000000 ,
b1111111100000000 I
b1111111100000000 W
b1000 -
b1000 V
b10 *
b1110 ?
1%
#520000
0%
#525000
b11111 .
b11011 /
b1111111101001011 +
b1111111101001011 H
b1111111101001011 X
b1111111101001011 ,
b1111111101001011 I
b1111111101001011 W
b1100 -
b1100 V
b11 *
b1111 ?
1%
#530000
0%
#535000
b10000 4
b10000 O
b10000 3
b10000 N
b0 *
b1000 0
b10000 2
b100000000 +
b100000000 H
b100000000 X
b0 ,
b0 I
b0 W
b0 -
b0 V
b11 @
b0 J
b0 L
b0 G
b1000 .
b100000 F
b0 /
b0 1
b0 ?
1%
#540000
0%
#545000
b1001 .
b1 /
b11101101 +
b11101101 H
b11101101 X
b0 L
b1111111110011110 ,
b1111111110011110 I
b1111111110011110 W
b10 -
b10 V
b1 *
b0 K
b10000 4
b10000 O
b10000 3
b10000 N
b1 ?
b0 J
b0 G
b100000 F
1%
#550000
0%
#555000
b0 6
b0 Q
b0 5
b0 P
b1010 .
b10 /
b10110101 +
b10110101 H
b10110101 X
b1111111101001011 ,
b1111111101001011 I
b1111111101001011 W
b100 -
b100 V
b10 *
b0 K
b0 M
b10000 4
b10000 O
b10000 3
b10000 N
b10 ?
b0 J
b0 L
b0 G
b100000 F
1%
#560000
0%
#565000
b0 6
b0 Q
b0 5
b0 P
b1011 .
b11 /
b1100010 +
b1100010 H
b1100010 X
b1111111100010011 ,
b1111111100010011 I
b1111111100010011 W
b110 -
b110 V
b11 *
b0 K
b0 M
b10000 4
b10000 O
b10000 3
b10000 N
b11 ?
b0 J
b0 L
b0 G
b100000 F
1%
#570000
0%
#575000
b0 6
b0 Q
b0 5
b0 P
b1100 .
b100 /
b0 +
b0 H
b0 X
b1111111100000000 ,
b1111111100000000 I
b1111111100000000 W
b1000 -
b1000 V
b100 *
b0 K
b0 M
b10000 4
b10000 O
b10000 3
b10000 N
b100 ?
b0 J
b0 L
b0 G
b100000 F
1%
#580000
0%
#585000
b0 6
b0 Q
b0 5
b0 P
b1101 .
b101 /
b0 J
b1111111110011110 +
b1111111110011110 H
b1111111110011110 X
b1111111100010011 ,
b1111111100010011 I
b1111111100010011 W
b1010 -
b1010 V
b101 *
b0 M
b10000 4
b10000 O
b10000 3
b10000 N
b101 ?
b0 L
b0 G
b100000 F
1%
#590000
0%
#595000
b0 6
b0 Q
b0 5
b0 P
b1110 .
b110 /
b1111111101001011 +
b1111111101001011 H
b1111111101001011 X
b1111111101001011 ,
b1111111101001011 I
b1111111101001011 W
b1100 -
b1100 V
b110 *
b0 K
b0 M
b10000 4
b10000 O
b10000 3
b10000 N
b110 ?
b0 J
b0 L
b0 G
b100000 F
1%
#600000
0%
#605000
b0 6
b0 Q
b0 5
b0 P
b1111 .
b111 /
b1111111100010011 +
b1111111100010011 H
b1111111100010011 X
b1111111110011110 ,
b1111111110011110 I
b1111111110011110 W
b1110 -
b1110 V
b111 *
b0 K
b0 M
b10000 4
b10000 O
b10000 3
b10000 N
b111 ?
b0 J
b0 L
b0 G
b100000 F
1%
#610000
0%
#615000
b100000000 +
b100000000 H
b100000000 X
b0 ,
b0 I
b0 W
b0 -
b0 V
b0 *
b0 4
b0 O
b0 3
b0 N
b11000 .
b10000 /
b1 1
b1000 ?
b0 J
b0 L
b0 G
b0 F
1%
#620000
0%
#625000
b11001 .
b10001 /
b11101101 +
b11101101 H
b11101101 X
b1111111110011110 ,
b1111111110011110 I
b1111111110011110 W
b10 -
b10 V
b1 *
b1001 ?
1%
#630000
0%
#635000
b11010 .
b10010 /
b10110101 +
b10110101 H
b10110101 X
b1111111101001011 ,
b1111111101001011 I
b1111111101001011 W
b100 -
b100 V
b10 *
b1010 ?
1%
#640000
0%
#645000
b11011 .
b10011 /
b1100010 +
b1100010 H
b1100010 X
b1111111100010011 ,
b1111111100010011 I
b1111111100010011 W
b110 -
b110 V
b11 *
b1011 ?
1%
#650000
0%
#655000
b11100 .
b10100 /
b0 +
b0 H
b0 X
b1111111100000000 ,
b1111111100000000 I
b1111111100000000 W
b1000 -
b1000 V
b100 *
b1100 ?
1%
#660000
0%
#665000
b11101 .
b10101 /
b1111111110011110 +
b1111111110011110 H
b1111111110011110 X
b1111111100010011 ,
b1111111100010011 I
b1111111100010011 W
b1010 -
b1010 V
b101 *
b1101 ?
1%
#670000
0%
#675000
b11110 .
b10110 /
b1111111101001011 +
b1111111101001011 H
b1111111101001011 X
b1111111101001011 ,
b1111111101001011 I
b1111111101001011 W
b1100 -
b1100 V
b110 *
b1110 ?
1%
#680000
0%
#685000
b11111 .
b10111 /
b1111111100010011 +
b1111111100010011 H
b1111111100010011 X
b1111111110011110 ,
b1111111110011110 I
b1111111110011110 W
b1110 -
b1110 V
b111 *
b1111 ?
1%
#690000
0%
#695000
b1000 4
b1000 O
b1000 3
b1000 N
b0 *
b10000 0
b0 2
b100000000 +
b100000000 H
b100000000 X
b0 ,
b0 I
b0 W
b0 -
b0 V
b100 @
b0 J
b0 L
b0 G
b10000 .
b10000 F
b0 /
b0 1
b0 ?
1%
#700000
0%
#705000
b10001 .
b1 /
b11111011 +
b11111011 H
b11111011 X
b0 L
b1111111111001110 ,
b1111111111001110 I
b1111111111001110 W
b1 -
b1 V
b1 *
b0 K
b1000 4
b1000 O
b1000 3
b1000 N
b1 ?
b0 J
b0 G
b10000 F
1%
#710000
0%
#715000
b0 6
b0 Q
b0 5
b0 P
b10010 .
b10 /
b11101101 +
b11101101 H
b11101101 X
b1111111110011110 ,
b1111111110011110 I
b1111111110011110 W
b10 -
b10 V
b10 *
b0 K
b0 M
b1000 4
b1000 O
b1000 3
b1000 N
b10 ?
b0 J
b0 L
b0 G
b10000 F
1%
#720000
0%
